{
  "accountLinkingWhitelistedDomains": null,
  "asin": "B01MAX808K",
  "averageRating": 4,
  "canDisable": true,
  "capabilities": null,
  "category": null,
  "description": "This skill gives you the top science posts from reddit's r/Science from the last 24 hours. You can ask for the latest post, or ask for the first to the fifth post. This content is user generated and may not be suitable for all ages. You can ask in the following ways:\n\n- Alexa, ask Science News for the first post\n- Alexa, ask Science News for the fifth post\n- Alexa, ask Science News for the recent post\n- Etc.\n\nThis content is user generated, and although it is heavily moderated, it may not be suitable for all ages.",
  "enablement": null,
  "exampleInteractions": [
    "Alexa, ask Science News for the latest post",
    "Alexa, ask Science News for the third post",
    "Alexa, ask Science News for the latest news"
  ],
  "firstReleaseDate": 1477464353.07,
  "homepageLinkText": null,
  "homepageLinkUrl": null,
  "id": "amzn1.ask.skill.b32619bc-b7a1-4438-a04b-bcf05a8b52a4",
  "imageAltText": "Science News icon",
  "imageUrl": "https://github.com/dale3h/alexa-skills-list/raw/master/skills/B01MAX808K/skill_icon",
  "inAppPurchasingSupported": false,
  "launchPhrase": "science news",
  "name": "Science News",
  "numberOfReviews": 1,
  "pamsPartnerId": null,
  "permissions": null,
  "privacyPolicyUrl": null,
  "shortDescription": "View the latest posts in the Science subreddit",
  "skillTypes": null,
  "stage": "live",
  "termsOfUseUrl": null,
  "vendorId": "M2C5UNU58ZVOEN",
  "vendorName": "Noah's Arc Development"
}
