{
  "accountLinkingWhitelistedDomains": null,
  "asin": "B01MY0DSEE",
  "averageRating": 4,
  "canDisable": true,
  "capabilities": null,
  "category": null,
  "description": "Cooking by weight is the most accurate and easy way to measure ingredients. Kitchen Scale tells you how much common ingredients weigh. You can find out how much a teaspoon, tablespoon, or cup of an ingredient weighs in grams or ounces.",
  "enablement": null,
  "exampleInteractions": [
    "Alexa ask Kitchen Scale how much does one cup of honey weigh",
    "Alexa ask Kitchen Scale how much does two cups of peanut butter weigh",
    "Alexa ask Kitchen Scale about bananas"
  ],
  "firstReleaseDate": 1482563954.263,
  "homepageLinkText": null,
  "homepageLinkUrl": null,
  "id": "amzn1.ask.skill.c9289c60-d1c4-4990-bd8d-feebec3f2d79",
  "imageAltText": "Kitchen Scale icon",
  "imageUrl": "https://github.com/dale3h/alexa-skills-list/raw/master/skills/B01MY0DSEE/skill_icon",
  "inAppPurchasingSupported": false,
  "launchPhrase": "kitchen scale",
  "name": "Kitchen Scale",
  "numberOfReviews": 3,
  "pamsPartnerId": null,
  "permissions": null,
  "privacyPolicyUrl": "http://www.luppes.com/Alexa/Privacy",
  "shortDescription": "This app tells you the weight of common baking ingredients.",
  "skillTypes": null,
  "stage": "live",
  "termsOfUseUrl": "http://www.luppes.com/Alexa/TermsOfUse",
  "vendorId": "M18OD70KDA1FDA",
  "vendorName": "Luppes Consulting, Inc."
}
