{
  "accountLinkingWhitelistedDomains": null,
  "asin": "B01EWECCWS",
  "averageRating": 4.7,
  "canDisable": true,
  "capabilities": null,
  "category": "Education",
  "description": "Explore important events and famous birthdays that happened today in history. Gain perspective on your day by learning about historical events that have shaped our world.",
  "enablement": null,
  "exampleInteractions": [
    "Alexa, ask Livy what happened today in history",
    "Alexa, ask Livy what happened on this day",
    null
  ],
  "firstReleaseDate": 1462176512.214,
  "homepageLinkText": null,
  "homepageLinkUrl": null,
  "id": "amzn1.echo-sdk-ams.app.9f97412f-e15e-482c-9f6b-deb735a89e92",
  "imageAltText": "Livy icon",
  "imageUrl": "https://github.com/dale3h/alexa-skills-list/raw/master/skills/B01EWECCWS/skill_icon",
  "inAppPurchasingSupported": false,
  "launchPhrase": "livy",
  "name": "Livy",
  "numberOfReviews": 6,
  "pamsPartnerId": null,
  "permissions": null,
  "privacyPolicyUrl": null,
  "shortDescription": "Learn what happened today in history, including major events and notable birthdays.",
  "skillTypes": null,
  "stage": "live",
  "termsOfUseUrl": null,
  "vendorId": "M2BBXDQHGUI0XU",
  "vendorName": "Cuttarug"
}
