{
  "accountLinkingWhitelistedDomains": null,
  "asin": "B01N1WX5WN",
  "averageRating": 0,
  "canDisable": true,
  "capabilities": null,
  "category": null,
  "description": "My first Alexa Skill with a selection of geography facts.",
  "enablement": null,
  "exampleInteractions": [
    "Alexa, open Geography Facts",
    "Give me a geography fact",
    null
  ],
  "firstReleaseDate": 1482994177.205,
  "homepageLinkText": null,
  "homepageLinkUrl": null,
  "id": "amzn1.ask.skill.10c02710-2ec2-450f-90fb-9eef78c26085",
  "imageAltText": "Geography Facts icon",
  "imageUrl": "https://github.com/dale3h/alexa-skills-list/raw/master/skills/B01N1WX5WN/skill_icon",
  "inAppPurchasingSupported": false,
  "launchPhrase": "geography facts",
  "name": "Geography Facts",
  "numberOfReviews": 0,
  "pamsPartnerId": null,
  "permissions": null,
  "privacyPolicyUrl": null,
  "shortDescription": "Geography Facts",
  "skillTypes": null,
  "stage": "live",
  "termsOfUseUrl": null,
  "vendorId": "MA1PZ1TGFIA9F",
  "vendorName": "yuhaw-su"
}
