{
  "accountLinkingWhitelistedDomains": null,
  "asin": "B01HKXCP4I",
  "averageRating": 4,
  "canDisable": true,
  "capabilities": null,
  "category": null,
  "description": "Real investors need more than stock price quotes. Instantly get professional-grade data on peers, multiples, financials, and valuation, including Street estimates! No account required for Alexa users. To invest like the top hedge funds in the world, ask about our desktop and mobile products at Sentieo.com.",
  "enablement": null,
  "exampleInteractions": [
    "Alexa, ask Sentieo what is the F Y Twenty Seventeen sales growth for A M Z N?",
    "Alexa, ask Sentieo what is the price earnings ratio for Amazon?",
    "Alexa, ask Sentieo who are the peers of T S L A?"
  ],
  "firstReleaseDate": 1467617252.108,
  "homepageLinkText": null,
  "homepageLinkUrl": null,
  "id": "amzn1.echo-sdk-ams.app.ab8fb10d-159d-48f4-b410-3061526b958c",
  "imageAltText": "Sentieo icon",
  "imageUrl": "https://github.com/dale3h/alexa-skills-list/raw/master/skills/B01HKXCP4I/skill_icon",
  "inAppPurchasingSupported": false,
  "launchPhrase": "sentieo",
  "name": "Sentieo",
  "numberOfReviews": 3,
  "pamsPartnerId": null,
  "permissions": null,
  "privacyPolicyUrl": "https://sentieo.com/content/legal/privacy-policy.html",
  "shortDescription": "Free Financial Data from the World's Most Advanced Equity Research Platform",
  "skillTypes": null,
  "stage": "live",
  "termsOfUseUrl": "https://sentieo.com/content/legal/terms-of-service.html",
  "vendorId": "M39BINPZAZ938W",
  "vendorName": "Sentieo"
}
