{
  "accountLinkingWhitelistedDomains": null,
  "asin": "B01IZTKIKE",
  "averageRating": 0,
  "canDisable": true,
  "capabilities": null,
  "category": null,
  "description": "Dr. Quadratic, the Root Doctor\n\nFind the roots of the quadratic equation with the quadratic formula.\n\nThe quadratic equation is of the form:\nAx² + Bx + C = 0, such that A not equal 0.\n\nAbout the quadratic formula\n\nTry...\n\nAlexa, ask Dr. Quadratic about the formula\nAlexa, ask Dr. Quadratic for help\n\nTo solve an quadratic equation try....\n\nthis can be done in several operations. \n1. Assign value to the coefficients, A, B, and C\n2. Calculate\n\nSome examples:\n\nAlexa, Open Dr. Quadratic\nlet A equal 3\nlet B equal 10\nlet C equal 2\ncalculate\n\nlet A equal 1\nlet B equal 2\nlet C equal -35\ncalculate\n\nlet A equal 1\nlet B equal 3.5\nlet C equal 7\ncalculate\n\nNotes:\n\nTo skip the skill intro you can say...\nOpen Dr. Quadratic and let B equal 5\n\nAt startup the default coefficients are A=1, B=0, C=0, so you can say....\n\nOpen Dr. Quadratic and calculate, which will solve the default equation\nx² = 0.",
  "enablement": null,
  "exampleInteractions": [
    "Alexa, ask doctor quadratic about the formula",
    "Alexa, open doctor quadratic and let A equal 3",
    "calculate"
  ],
  "firstReleaseDate": 1470143510.408,
  "homepageLinkText": null,
  "homepageLinkUrl": null,
  "id": "amzn1.ask.skill.6cdd2ab9-2f84-4c36-9c6f-20100a7d5c9c",
  "imageAltText": "The Quadratic Root Doctor icon",
  "imageUrl": "https://github.com/dale3h/alexa-skills-list/raw/master/skills/B01IZTKIKE/skill_icon",
  "inAppPurchasingSupported": false,
  "launchPhrase": "doctor quadratic",
  "name": "The Quadratic Root Doctor",
  "numberOfReviews": 0,
  "pamsPartnerId": null,
  "permissions": null,
  "privacyPolicyUrl": null,
  "shortDescription": "Dr. Quadratic, the Root Doctor\n\nFind the roots of the quadratic equation with the quadratic formula.",
  "skillTypes": null,
  "stage": "live",
  "termsOfUseUrl": null,
  "vendorId": "M12N2THNU5U76U",
  "vendorName": "Don Holmberg"
}
