{
  "accountLinkingWhitelistedDomains": null,
  "asin": "B01N2Q9XOG",
  "averageRating": 1,
  "canDisable": true,
  "capabilities": null,
  "category": null,
  "description": "A simple game that allows you to check how good you know capitals of world countries. Everyone knows Paris, Rome or Buenos Aires but do you know what is a capital of Colombia or Ghana? Take up the  challenge, learn and have fun. More than 200 hundred countries included.",
  "enablement": null,
  "exampleInteractions": [
    "Alexa, open world capitals",
    "help",
    "don't know"
  ],
  "firstReleaseDate": 1481023167.256,
  "homepageLinkText": null,
  "homepageLinkUrl": null,
  "id": "amzn1.ask.skill.38899241-ff42-425b-984e-9f5993270e76",
  "imageAltText": "WorldCapitals icon",
  "imageUrl": "https://github.com/dale3h/alexa-skills-list/raw/master/skills/B01N2Q9XOG/skill_icon",
  "inAppPurchasingSupported": false,
  "launchPhrase": "world capitals",
  "name": "WorldCapitals",
  "numberOfReviews": 1,
  "pamsPartnerId": null,
  "permissions": null,
  "privacyPolicyUrl": null,
  "shortDescription": "learn & play world capitals",
  "skillTypes": null,
  "stage": "live",
  "termsOfUseUrl": null,
  "vendorId": "M25RHARI3KCSOO",
  "vendorName": "Softmil"
}
