{
  "accountLinkingWhitelistedDomains": null,
  "asin": "B01FT3GF4C",
  "averageRating": 2.9,
  "canDisable": true,
  "capabilities": null,
  "category": null,
  "description": "Can't find the channel you are looking for in the Dish Network guide?  Have Alexa ask Channel Finder, a tool to find channel numbers by asking with the channel name.",
  "enablement": null,
  "exampleInteractions": [
    "Alexa, ask channel finder what is the channel number for comedy central?",
    "Alexa, ask channel finder what channel is vice land?",
    "Alexa, ask channel finder where is Nickelodeon?"
  ],
  "firstReleaseDate": 1464259110.71,
  "homepageLinkText": null,
  "homepageLinkUrl": null,
  "id": "amzn1.echo-sdk-ams.app.c0d8baf8-9003-46ba-a370-79d3b8875379",
  "imageAltText": "Channel Finder icon",
  "imageUrl": "https://github.com/dale3h/alexa-skills-list/raw/master/skills/B01FT3GF4C/skill_icon",
  "inAppPurchasingSupported": false,
  "launchPhrase": "channel finder",
  "name": "Channel Finder",
  "numberOfReviews": 5,
  "pamsPartnerId": null,
  "permissions": null,
  "privacyPolicyUrl": null,
  "shortDescription": "Channel number finder for Sacramento region Dish Network",
  "skillTypes": null,
  "stage": "live",
  "termsOfUseUrl": null,
  "vendorId": "M3T42BKGNMNJ6T",
  "vendorName": "Matt Carter"
}
