{
  "accountLinkingWhitelistedDomains": null,
  "asin": "B01MRKEX4Z",
  "averageRating": 0,
  "canDisable": true,
  "capabilities": null,
  "category": null,
  "description": null,
  "enablement": null,
  "exampleInteractions": null,
  "firstReleaseDate": 1480068310.878,
  "homepageLinkText": null,
  "homepageLinkUrl": null,
  "id": "amzn1.ask.skill.e5fb2127-dc44-4f26-9f2a-b0b35489302b",
  "imageAltText": null,
  "imageUrl": "https://github.com/dale3h/alexa-skills-list/raw/master/skills/B01MRKEX4Z/skill_icon",
  "inAppPurchasingSupported": false,
  "launchPhrase": null,
  "name": "Anthony Sibley",
  "numberOfReviews": 0,
  "pamsPartnerId": null,
  "permissions": null,
  "privacyPolicyUrl": null,
  "shortDescription": null,
  "skillTypes": null,
  "stage": "live",
  "termsOfUseUrl": null,
  "vendorId": "M2QW1ERQ2X40W5",
  "vendorName": "Anthony Sibley"
}
