{
  "accountLinkingWhitelistedDomains": null,
  "asin": "B01GD4DEDQ",
  "averageRating": 0,
  "canDisable": true,
  "capabilities": null,
  "category": null,
  "description": "Interesting facts about Prince the musician with information",
  "enablement": null,
  "exampleInteractions": [
    "Alexa, open Pop Star Facts",
    "Alexa, ask Pop Star Facts to make it Purple Rain",
    "Alexa, ask Pop Star Facts to share a fact"
  ],
  "firstReleaseDate": 1468934854.782,
  "homepageLinkText": null,
  "homepageLinkUrl": null,
  "id": "amzn1.echo-sdk-ams.app.dce2fea1-ffeb-441f-8e58-9b9c6d5f8f56",
  "imageAltText": "Pop Star Facts icon",
  "imageUrl": "https://github.com/dale3h/alexa-skills-list/raw/master/skills/B01GD4DEDQ/skill_icon",
  "inAppPurchasingSupported": false,
  "launchPhrase": "pop star facts",
  "name": "Pop Star Facts",
  "numberOfReviews": 0,
  "pamsPartnerId": null,
  "permissions": null,
  "privacyPolicyUrl": null,
  "shortDescription": "Interesting facts about Prince the musician",
  "skillTypes": null,
  "stage": "live",
  "termsOfUseUrl": null,
  "vendorId": "M337YRXKIMH9GT",
  "vendorName": "Blue Crystal Web Design"
}
