{
  "accountLinkingWhitelistedDomains": null,
  "asin": "B01M16D595",
  "averageRating": 0,
  "canDisable": true,
  "capabilities": null,
  "category": null,
  "description": "Ask Alexa to return quotes from the Tao of Programming\nhttp://www.canonical.org/~kragen/tao-of-programming.html \n\nThis is in no way affiliated with the Tao of Programming\n\nThe code the back end can be found:\nhttps://github.com/orthros/alexa-tao-of-programming",
  "enablement": null,
  "exampleInteractions": [
    "Alexa, ask Unofficial Programming Tao to tell me about the tao",
    "Alexa, ask Unofficial Programming Tao to tell me something about the tao",
    "Alexa, ask Unofficial Programming Tao to tell us what the tao says"
  ],
  "firstReleaseDate": 1475919700.028,
  "homepageLinkText": null,
  "homepageLinkUrl": null,
  "id": "amzn1.ask.skill.2292237e-7bf6-4fcb-9541-655f70f95034",
  "imageAltText": "Unoficial Tao of Programming icon",
  "imageUrl": "https://github.com/dale3h/alexa-skills-list/raw/master/skills/B01M16D595/skill_icon",
  "inAppPurchasingSupported": false,
  "launchPhrase": "unofficial programming tao",
  "name": "Unoficial Tao of Programming",
  "numberOfReviews": 0,
  "pamsPartnerId": null,
  "permissions": null,
  "privacyPolicyUrl": null,
  "shortDescription": "Ask Alexa to quote from the Tao of Programming",
  "skillTypes": null,
  "stage": "live",
  "termsOfUseUrl": null,
  "vendorId": "M2XW81O4T3AJIQ",
  "vendorName": "orthros"
}
