{
  "accountLinkingWhitelistedDomains": null,
  "asin": "B01HLOPNBI",
  "averageRating": 5,
  "canDisable": true,
  "capabilities": null,
  "category": null,
  "description": "This is a flashcard skill that helps you learn the network ports used by Citrix Products",
  "enablement": null,
  "exampleInteractions": [
    "Alexa, start flash port quiz",
    "Start game",
    "The answer is 1494"
  ],
  "firstReleaseDate": 1467964665.157,
  "homepageLinkText": null,
  "homepageLinkUrl": null,
  "id": "amzn1.echo-sdk-ams.app.de125342-4326-449a-9b9d-f85666b1bb34",
  "imageAltText": "Flash Card Quiz for Citrix Ports icon",
  "imageUrl": "https://github.com/dale3h/alexa-skills-list/raw/master/skills/B01HLOPNBI/skill_icon",
  "inAppPurchasingSupported": false,
  "launchPhrase": "flash port quiz",
  "name": "Flash Card Quiz for Citrix Ports",
  "numberOfReviews": 1,
  "pamsPartnerId": null,
  "permissions": null,
  "privacyPolicyUrl": "http://tokeshi.com/node/5159",
  "shortDescription": "Flashcards for ports used by Citrix products",
  "skillTypes": null,
  "stage": "live",
  "termsOfUseUrl": "http://tokeshi.com/node/5157",
  "vendorId": "M3UYPX7KINTFLJ",
  "vendorName": "Tokeshi.com"
}
