{
  "accountLinkingWhitelistedDomains": null,
  "asin": "B01M0SP3QN",
  "averageRating": 5,
  "canDisable": true,
  "capabilities": null,
  "category": null,
  "description": "Deep thoughts is a skill to give you something to think about. Some are insightful, some are not. \n\nAsk me for something thoughtful!",
  "enablement": null,
  "exampleInteractions": [
    "Alexa, start deep thoughts",
    "Alexa, launch deep thoughts",
    "Alexa, open deep thoughts"
  ],
  "firstReleaseDate": 1475100772.226,
  "homepageLinkText": null,
  "homepageLinkUrl": null,
  "id": "amzn1.ask.skill.05101053-3ee5-4917-a32f-2bf982b83de6",
  "imageAltText": "Deep Thoughts icon",
  "imageUrl": "https://github.com/dale3h/alexa-skills-list/raw/master/skills/B01M0SP3QN/skill_icon",
  "inAppPurchasingSupported": false,
  "launchPhrase": "deep thoughts",
  "name": "Deep Thoughts",
  "numberOfReviews": 3,
  "pamsPartnerId": null,
  "permissions": null,
  "privacyPolicyUrl": null,
  "shortDescription": "A skill that tells you something thoughtful whenever you ask.",
  "skillTypes": null,
  "stage": "live",
  "termsOfUseUrl": null,
  "vendorId": "M3KDIOO0CK6GNI",
  "vendorName": "BlogAndCode"
}
