{
  "accountLinkingWhitelistedDomains": null,
  "asin": "B01KATE4JI",
  "averageRating": 0,
  "canDisable": true,
  "capabilities": null,
  "category": null,
  "description": "Facts about Singapore",
  "enablement": null,
  "exampleInteractions": [
    "Alexa, ask singapore facts to tell me a singapore fact",
    "Alexa, ask singapore facts to give me a singapore fact",
    "Alexa, ask singapore facts to provide me with a singapore fact"
  ],
  "firstReleaseDate": 1472036529.168,
  "homepageLinkText": null,
  "homepageLinkUrl": null,
  "id": "amzn1.ask.skill.f2b13438-5442-4468-a6e5-5f0ffe256bcc",
  "imageAltText": "Singapore  Facts icon",
  "imageUrl": "https://github.com/dale3h/alexa-skills-list/raw/master/skills/B01KATE4JI/skill_icon",
  "inAppPurchasingSupported": false,
  "launchPhrase": "singapore facts",
  "name": "Singapore  Facts",
  "numberOfReviews": 0,
  "pamsPartnerId": null,
  "permissions": null,
  "privacyPolicyUrl": null,
  "shortDescription": "Facts about Singapore",
  "skillTypes": null,
  "stage": "live",
  "termsOfUseUrl": null,
  "vendorId": "M2WN7389YODPGC",
  "vendorName": "MSG Associates "
}
