{
  "accountLinkingWhitelistedDomains": null,
  "asin": "B01MRUL00G",
  "averageRating": 0,
  "canDisable": true,
  "capabilities": null,
  "category": null,
  "description": "The Discovery Ski Area Snow Report brought to you by SnoCountry brings you the latest snow fall, snow surface conditions,  base depth, trail, and lift operations information.",
  "enablement": null,
  "exampleInteractions": [
    "Alexa, open Discovery Ski Area",
    "Alexa, ask Discovery Ski Area for the snow report",
    "Alexa, ask Discovery Ski Area for latest conditions"
  ],
  "firstReleaseDate": 1481073597.853,
  "homepageLinkText": null,
  "homepageLinkUrl": null,
  "id": "amzn1.ask.skill.7d8a7814-0521-44d4-958d-e206b27102ca",
  "imageAltText": "Snow Report for Discovery Ski Area icon",
  "imageUrl": "https://github.com/dale3h/alexa-skills-list/raw/master/skills/B01MRUL00G/skill_icon",
  "inAppPurchasingSupported": false,
  "launchPhrase": "discovery ski area",
  "name": "Snow Report for Discovery Ski Area",
  "numberOfReviews": 0,
  "pamsPartnerId": null,
  "permissions": null,
  "privacyPolicyUrl": null,
  "shortDescription": "The Discovery Ski Area Snow Report brought to you by SnoCountry provides the latest ski and snowboarding conditions for Discovery Ski Area.",
  "skillTypes": null,
  "stage": "live",
  "termsOfUseUrl": null,
  "vendorId": "M2QMZCV87DXXRY",
  "vendorName": "SnoCountry"
}
