{
  "accountLinkingWhitelistedDomains": null,
  "asin": "B01J29W3OU",
  "averageRating": 0,
  "canDisable": true,
  "capabilities": null,
  "category": null,
  "description": "This Alexa App provides fun facts about Wales simply by asking, \"Alexa, ask Wales facts to tell me a fact\". There are no prerequisites or account requirements. It does not collect any information from the user.",
  "enablement": null,
  "exampleInteractions": [
    "Alexa ask wales facts to give me a wales fact.",
    "Alexa ask wales facts to tell me a wales fact.",
    "Alexa ask wales facts to give me some wales information."
  ],
  "firstReleaseDate": 1469528782.639,
  "homepageLinkText": null,
  "homepageLinkUrl": null,
  "id": "amzn1.ask.skill.43e7da54-7852-44c1-b227-ae41a458dcbb",
  "imageAltText": "Wales Facts icon",
  "imageUrl": "https://github.com/dale3h/alexa-skills-list/raw/master/skills/B01J29W3OU/skill_icon",
  "inAppPurchasingSupported": false,
  "launchPhrase": "wales facts",
  "name": "Wales Facts",
  "numberOfReviews": 0,
  "pamsPartnerId": null,
  "permissions": null,
  "privacyPolicyUrl": null,
  "shortDescription": "This Alexa App provides fun facts about the country of Wales.",
  "skillTypes": null,
  "stage": "live",
  "termsOfUseUrl": null,
  "vendorId": "M11FNQB3SQ7NSK",
  "vendorName": "Jason Sit"
}
