{
  "accountLinkingWhitelistedDomains": null,
  "asin": "B01KTVYLY0",
  "averageRating": 0,
  "canDisable": true,
  "capabilities": null,
  "category": null,
  "description": "Get the latest available, from NEW YORK DATA GOV,  SAT scores for New York City Schools.   Search by Borough  and/or schools name first letter.  or  Get top scoring schools in Math, Reading or Writing.",
  "enablement": null,
  "exampleInteractions": [
    "Alexa, ask, s. a. t. for county Manhattan",
    "Ask, s. a. t. for county Bronx first letter h",
    "Ask, s. a. t. for math scores"
  ],
  "firstReleaseDate": 1475921508.176,
  "homepageLinkText": null,
  "homepageLinkUrl": null,
  "id": "amzn1.ask.skill.61f18d95-8ebd-4e39-a2fc-e6fd99d2c727",
  "imageAltText": "New York City SAT Scores icon",
  "imageUrl": "https://github.com/dale3h/alexa-skills-list/raw/master/skills/B01KTVYLY0/skill_icon",
  "inAppPurchasingSupported": false,
  "launchPhrase": "s. a. t.",
  "name": "New York City SAT Scores",
  "numberOfReviews": 0,
  "pamsPartnerId": null,
  "permissions": null,
  "privacyPolicyUrl": "http://www.digitalspring.com/apps/mtprivacy",
  "shortDescription": "Know the latest (2012) average SAT scores of New York City Schools. Search by Borough or get Top performing schools.  Alexa ask, s. a. t. for math scores",
  "skillTypes": null,
  "stage": "live",
  "termsOfUseUrl": "http://www.digitalspring.com/apps/mtprivacy",
  "vendorId": "M3NJW21C06UZWH",
  "vendorName": "Digital Spring Apps"
}
