{
  "accountLinkingWhitelistedDomains": null,
  "asin": "B01M7YD2R2",
  "averageRating": 0,
  "canDisable": true,
  "capabilities": null,
  "category": null,
  "description": "Find National Parks by state in the United States.",
  "enablement": null,
  "exampleInteractions": [
    "Alexa Open NationalParkFInder",
    "Find me national parks in alaska",
    "How many parks are in colorado"
  ],
  "firstReleaseDate": 1479202499.619,
  "homepageLinkText": null,
  "homepageLinkUrl": null,
  "id": "amzn1.ask.skill.25b1a77b-ec79-4566-8674-f4192f66b549",
  "imageAltText": "National Park Finder icon",
  "imageUrl": "https://github.com/dale3h/alexa-skills-list/raw/master/skills/B01M7YD2R2/skill_icon",
  "inAppPurchasingSupported": false,
  "launchPhrase": "national park finder",
  "name": "National Park Finder",
  "numberOfReviews": 0,
  "pamsPartnerId": null,
  "permissions": null,
  "privacyPolicyUrl": null,
  "shortDescription": "Find National Parks by state",
  "skillTypes": null,
  "stage": "live",
  "termsOfUseUrl": null,
  "vendorId": "M1PC75IZWH209L",
  "vendorName": "Brian Wyka"
}
