{
  "accountLinkingWhitelistedDomains": null,
  "asin": "B01B79Q5KQ",
  "averageRating": 1.5,
  "canDisable": true,
  "capabilities": null,
  "category": "Productivity",
  "description": "21 Dayz will help guide you in your journey to developing new business or personal habits with daily intents and affirmations. Start by selecting business or personal, then a subcategory like finance or growth for business or health and fitness or personal development for the personal category. Once you have made your selections, the journey begins.",
  "enablement": null,
  "exampleInteractions": [
    "Alexa, start 21 Dayz",
    "Alexa, ask 21 Dayz for today's intents",
    "Alexa, ask 21 Dayz to restart"
  ],
  "firstReleaseDate": 1454044656.337,
  "homepageLinkText": null,
  "homepageLinkUrl": null,
  "id": "amzn1.echo-sdk-ams.app.a4055920-713d-4665-bb6b-ac6a90cc0f71",
  "imageAltText": "21 Dayz icon",
  "imageUrl": "https://github.com/dale3h/alexa-skills-list/raw/master/skills/B01B79Q5KQ/skill_icon",
  "inAppPurchasingSupported": false,
  "launchPhrase": "twenty one days",
  "name": "21 Dayz",
  "numberOfReviews": 2,
  "pamsPartnerId": null,
  "permissions": null,
  "privacyPolicyUrl": null,
  "shortDescription": "As the saying goes, it takes at least 21 days to build a habit. Use 21 Dayz to help guide you in your journey to developing new business or personal habits.",
  "skillTypes": null,
  "stage": "live",
  "termsOfUseUrl": null,
  "vendorId": "M2AUIT9PSRTSJV",
  "vendorName": "Agile Planners"
}
