{
  "accountLinkingWhitelistedDomains": null,
  "asin": "B01NCP8NAN",
  "averageRating": 4.5,
  "canDisable": true,
  "capabilities": null,
  "category": null,
  "description": "Great for parties or annoying people at your office :) Please use responsibly. Don't AIRHORN and drive.",
  "enablement": null,
  "exampleInteractions": [
    "Alexa, open air horn",
    "Alexa, ask air horn to play",
    "Alexa, open air horn and play"
  ],
  "firstReleaseDate": 1483172337.638,
  "homepageLinkText": null,
  "homepageLinkUrl": null,
  "id": "amzn1.ask.skill.397a53c1-ee8b-4b39-9eea-05d229a80dd6",
  "imageAltText": "AIRHORN icon",
  "imageUrl": "https://github.com/dale3h/alexa-skills-list/raw/master/skills/B01NCP8NAN/skill_icon",
  "inAppPurchasingSupported": false,
  "launchPhrase": "air horn",
  "name": "AIRHORN",
  "numberOfReviews": 2,
  "pamsPartnerId": null,
  "permissions": null,
  "privacyPolicyUrl": null,
  "shortDescription": "You want air horn? We've got air horn!",
  "skillTypes": null,
  "stage": "live",
  "termsOfUseUrl": null,
  "vendorId": "MCQT8N6K9U9DQ",
  "vendorName": "bspeagle.com"
}
