{
  "accountLinkingWhitelistedDomains": null,
  "asin": "B01MCVZIOM",
  "averageRating": 0,
  "canDisable": true,
  "capabilities": null,
  "category": null,
  "description": "The Magic Mountain Snow Report brought to you by SnoCountry brings you the latest snow fall, snow surface conditions,  base depth, trail, and lift operations information.",
  "enablement": null,
  "exampleInteractions": [
    "Alexa, open Magic Mountain",
    "Alexa, ask Magic Mountain for the snow report",
    "Alexa, ask Magic Mountain for latest conditions"
  ],
  "firstReleaseDate": 1477080815.405,
  "homepageLinkText": null,
  "homepageLinkUrl": null,
  "id": "amzn1.ask.skill.5e53901b-3bdc-46f5-855e-7c73e121ddd5",
  "imageAltText": "Snow Report for Magic Mountain icon",
  "imageUrl": "https://github.com/dale3h/alexa-skills-list/raw/master/skills/B01MCVZIOM/skill_icon",
  "inAppPurchasingSupported": false,
  "launchPhrase": "magic mountain",
  "name": "Snow Report for Magic Mountain",
  "numberOfReviews": 0,
  "pamsPartnerId": null,
  "permissions": null,
  "privacyPolicyUrl": null,
  "shortDescription": "The Magic Mountain Snow Report brought to you by SnoCountry provides the latest ski and snowboarding conditions for Magic Mountain.",
  "skillTypes": null,
  "stage": "live",
  "termsOfUseUrl": null,
  "vendorId": "M2QMZCV87DXXRY",
  "vendorName": "SnoCountry"
}
