{
  "accountLinkingWhitelistedDomains": null,
  "asin": "B01IRHJ9BS",
  "averageRating": 0,
  "canDisable": true,
  "capabilities": null,
  "category": null,
  "description": "This skill tells the user about who was president of the United States of America.",
  "enablement": null,
  "exampleInteractions": [
    "Alexa, open american presidents and tell me a fact",
    "Alexa, open american presidents and give me a fact",
    "Alexa, tell american presidents to tell me something"
  ],
  "firstReleaseDate": 1469181448.983,
  "homepageLinkText": null,
  "homepageLinkUrl": null,
  "id": "amzn1.ask.skill.f3fb8eb1-7547-40ea-aa68-7976fd0a5eef",
  "imageAltText": "United States Presidents icon",
  "imageUrl": "https://github.com/dale3h/alexa-skills-list/raw/master/skills/B01IRHJ9BS/skill_icon",
  "inAppPurchasingSupported": false,
  "launchPhrase": "american presidents",
  "name": "United States Presidents",
  "numberOfReviews": 0,
  "pamsPartnerId": null,
  "permissions": null,
  "privacyPolicyUrl": null,
  "shortDescription": "List of United States Presidents",
  "skillTypes": null,
  "stage": "live",
  "termsOfUseUrl": null,
  "vendorId": "MG3V60SB1R79V",
  "vendorName": "Greg Szczygiel"
}
