{
  "accountLinkingWhitelistedDomains": null,
  "asin": "B01DL568EM",
  "averageRating": 2.5,
  "canDisable": true,
  "capabilities": null,
  "category": "Entertainment",
  "description": "Have a whale of a time with this whale themed trivia skill!",
  "enablement": null,
  "exampleInteractions": [
    "Alexa, ask whale trivia for a new game.",
    "The answer is 2.",
    "Peace out."
  ],
  "firstReleaseDate": 1459946022.308,
  "homepageLinkText": null,
  "homepageLinkUrl": null,
  "id": "amzn1.echo-sdk-ams.app.7aa469fc-63f2-458e-a073-828c2ecbd0ca",
  "imageAltText": "Whale Trivia icon",
  "imageUrl": "https://github.com/dale3h/alexa-skills-list/raw/master/skills/B01DL568EM/skill_icon",
  "inAppPurchasingSupported": false,
  "launchPhrase": "whale trivia",
  "name": "Whale Trivia",
  "numberOfReviews": 2,
  "pamsPartnerId": null,
  "permissions": null,
  "privacyPolicyUrl": null,
  "shortDescription": "Trivia game about whales",
  "skillTypes": null,
  "stage": "live",
  "termsOfUseUrl": null,
  "vendorId": "M4R7MC7TVPXYI",
  "vendorName": "DPT2"
}
