{
  "accountLinkingWhitelistedDomains": null,
  "asin": "B01LXC5HPT",
  "averageRating": 0,
  "canDisable": true,
  "capabilities": null,
  "category": null,
  "description": "The Panorama Mountain Snow Report brought to you by SnoCountry brings you the latest snow fall, snow surface conditions,  base depth, trail, and lift operations information.",
  "enablement": null,
  "exampleInteractions": [
    "Alexa, ask Panorama Mountain for the snow report",
    "Alexa, open Panorama Mountain",
    "Alexa, ask Panorama Mountain for latest conditions"
  ],
  "firstReleaseDate": 1476950201.067,
  "homepageLinkText": null,
  "homepageLinkUrl": null,
  "id": "amzn1.ask.skill.2064ca8b-4c65-4b72-8cd9-a4489853b452",
  "imageAltText": "Snow Report for Panorama Mountain icon",
  "imageUrl": "https://github.com/dale3h/alexa-skills-list/raw/master/skills/B01LXC5HPT/skill_icon",
  "inAppPurchasingSupported": false,
  "launchPhrase": "panorama mountain",
  "name": "Snow Report for Panorama Mountain",
  "numberOfReviews": 0,
  "pamsPartnerId": null,
  "permissions": null,
  "privacyPolicyUrl": null,
  "shortDescription": "The Panorama Mountain Snow Report brought to you by SnoCountry provides the latest ski and snowboarding conditions for Panorama Mountain.",
  "skillTypes": null,
  "stage": "live",
  "termsOfUseUrl": null,
  "vendorId": "M2QMZCV87DXXRY",
  "vendorName": "SnoCountry"
}
