{
  "accountLinkingWhitelistedDomains": null,
  "asin": "B01E6072QE",
  "averageRating": 0,
  "canDisable": true,
  "capabilities": null,
  "category": null,
  "description": "This skill WILL change your life. The amount of dinosaur trivia that will be bouncing around your head will amaze everyone. You will be the life of any party you go to. You will astound your friends. What are you waiting for!?\n\nContact me at tinystarship.com if you have any questions / comments.",
  "enablement": null,
  "exampleInteractions": [
    "Alexa, Open Dinosaur Facts",
    "Alexa, Launch Dinosaur Facts and tell me a fact",
    "Alexa, Start Dinosaur Facts and give me a fact"
  ],
  "firstReleaseDate": 1460673174.82,
  "homepageLinkText": null,
  "homepageLinkUrl": null,
  "id": "amzn1.echo-sdk-ams.app.a62131ee-2859-4ce8-9b25-14b5a496b3fd",
  "imageAltText": "Dinosaur Facts icon",
  "imageUrl": "https://github.com/dale3h/alexa-skills-list/raw/master/skills/B01E6072QE/skill_icon",
  "inAppPurchasingSupported": false,
  "launchPhrase": "dinosaur facts",
  "name": "Dinosaur Facts",
  "numberOfReviews": 0,
  "pamsPartnerId": null,
  "permissions": null,
  "privacyPolicyUrl": null,
  "shortDescription": "Do you like Dinosaurs? Of course you down. Enable this skill to learn even MORE about dinosaurs!",
  "skillTypes": null,
  "stage": "live",
  "termsOfUseUrl": null,
  "vendorId": "M1AG5RV3ET6105",
  "vendorName": "Tiny Starship"
}
