{
  "accountLinkingWhitelistedDomains": null,
  "asin": "B01J6KAFKE",
  "averageRating": 0,
  "canDisable": true,
  "capabilities": null,
  "category": null,
  "description": "Paddock Reporter keeps you up to date with whats happening in the world of Formula One racing.\n\nYou can ask Paddock Reporter the following:\n- Who won the last race?\n- When is the next race?\n- What are the driver standings?",
  "enablement": null,
  "exampleInteractions": [
    "Alexa, ask Paddock Reporter who won the last race",
    "When is the next race",
    "Where is the next race"
  ],
  "firstReleaseDate": 1470661654.958,
  "homepageLinkText": null,
  "homepageLinkUrl": null,
  "id": "amzn1.echo-sdk-ams.app.cd7e422d-9df4-4309-a7b9-7d1017f6de2b",
  "imageAltText": "Paddock Reporter icon",
  "imageUrl": "https://github.com/dale3h/alexa-skills-list/raw/master/skills/B01J6KAFKE/skill_icon",
  "inAppPurchasingSupported": false,
  "launchPhrase": "paddock reporter",
  "name": "Paddock Reporter",
  "numberOfReviews": 0,
  "pamsPartnerId": null,
  "permissions": null,
  "privacyPolicyUrl": "",
  "shortDescription": "Paddock Reporter gives you Formula 1 racing results and updates.",
  "skillTypes": null,
  "stage": "live",
  "termsOfUseUrl": "",
  "vendorId": "M2RWR4RYG7KCH8",
  "vendorName": "Kevin Epstein"
}
