{
  "accountLinkingWhitelistedDomains": null,
  "asin": "B01N3WEX2Z",
  "averageRating": 0,
  "canDisable": true,
  "capabilities": null,
  "category": null,
  "description": "This is my first go around with Alexa so give it a shot to learn some interesting random facts. In the future this will be filled with so many random facts!!!!",
  "enablement": null,
  "exampleInteractions": [
    "Alexa , ask fun stuff to tell me a fact",
    "Alexa , ask fun stuff to give me a fact",
    "Alexa , ask fun stuff to tell me trivia"
  ],
  "firstReleaseDate": 1478848410.679,
  "homepageLinkText": null,
  "homepageLinkUrl": null,
  "id": "amzn1.ask.skill.b379ebb8-333c-4216-aefb-e2e74861bfff",
  "imageAltText": "Fun Stuff icon",
  "imageUrl": "https://github.com/dale3h/alexa-skills-list/raw/master/skills/B01N3WEX2Z/skill_icon",
  "inAppPurchasingSupported": false,
  "launchPhrase": "fun stuff",
  "name": "Fun Stuff",
  "numberOfReviews": 0,
  "pamsPartnerId": null,
  "permissions": null,
  "privacyPolicyUrl": null,
  "shortDescription": "Few Random Facts",
  "skillTypes": null,
  "stage": "live",
  "termsOfUseUrl": null,
  "vendorId": "M2QWYCY1GVJQZM",
  "vendorName": "MattyG"
}
