{
  "accountLinkingWhitelistedDomains": null,
  "asin": "B01E9Z3UVC",
  "averageRating": 3.4,
  "canDisable": true,
  "capabilities": null,
  "category": null,
  "description": "Opening Bell allows you to speak a company's natural name to get their stock price and daily percentage change. You'll get a short, yet informative response without the hassle of trying to remember a company's ticker symbol.\n\nBring the stock market to your Echo device with Opening Bell!\n\n --\n\nOpening Bell retrieves stock data from Markit On Demand and is not guaranteed to have real-time stock price information and is therefore only recommended to be used as a general reference and not for making stock trading decisions.",
  "enablement": null,
  "exampleInteractions": [
    "Alexa, ask Opening Bell for Tesla.",
    "Alexa, ask Opening Bell for the price of Apple.",
    "Alexa, ask Opening Bell for the price of Microsoft stock."
  ],
  "firstReleaseDate": 1461191570.228,
  "homepageLinkText": null,
  "homepageLinkUrl": null,
  "id": "amzn1.echo-sdk-ams.app.e46fdef7-3ce7-4374-9135-05eac31a70cb",
  "imageAltText": "Opening Bell icon",
  "imageUrl": "https://github.com/dale3h/alexa-skills-list/raw/master/skills/B01E9Z3UVC/skill_icon",
  "inAppPurchasingSupported": false,
  "launchPhrase": "opening bell",
  "name": "Opening Bell",
  "numberOfReviews": 10,
  "pamsPartnerId": null,
  "permissions": null,
  "privacyPolicyUrl": null,
  "shortDescription": "Retrieve stock quotes of publicly traded companies (on NASDAQ & NYSE exchanges) using the company name, not the ticker symbol.",
  "skillTypes": null,
  "stage": "live",
  "termsOfUseUrl": null,
  "vendorId": "M17TLPFLN9KXO2",
  "vendorName": "Nick Schwab"
}
