{
  "accountLinkingWhitelistedDomains": null,
  "asin": "B01KSSCKTC",
  "averageRating": 0,
  "canDisable": true,
  "capabilities": null,
  "category": null,
  "description": "Guess the Animal is a fun and educational game that your family will have fun playing.  Each animal is described, starting with where they live and a brief description and the clues end with a more precise clue that will guide the player towards the correct animal.  There are a series of animals described, get the most correct to win.  More animals will be added over time.",
  "enablement": null,
  "exampleInteractions": [
    "Alexa, open Guess the Animal and start a new game",
    "repeat the clues",
    "play a new game"
  ],
  "firstReleaseDate": 1472454168.4,
  "homepageLinkText": null,
  "homepageLinkUrl": null,
  "id": "amzn1.ask.skill.2855c88b-f4af-4010-acdf-f80a00c7f604",
  "imageAltText": "Guess The Animal icon",
  "imageUrl": "https://github.com/dale3h/alexa-skills-list/raw/master/skills/B01KSSCKTC/skill_icon",
  "inAppPurchasingSupported": false,
  "launchPhrase": "guess the animal",
  "name": "Guess The Animal",
  "numberOfReviews": 0,
  "pamsPartnerId": null,
  "permissions": null,
  "privacyPolicyUrl": null,
  "shortDescription": "Guess the Animal is a simple fun game.  Alexa describes a series of animals and you guess the animal that is described.",
  "skillTypes": null,
  "stage": "live",
  "termsOfUseUrl": null,
  "vendorId": "M36HD24D1HVX4B",
  "vendorName": "Spitfire Game Studios LLC"
}
