{
  "accountLinkingWhitelistedDomains": null,
  "asin": "B01KF22RE4",
  "averageRating": 0,
  "canDisable": true,
  "capabilities": null,
  "category": null,
  "description": "Get motivation from Alexa to give you the extra inspiration to power up the rest of your day.",
  "enablement": null,
  "exampleInteractions": [
    "Alexa, start give motivation",
    "",
    ""
  ],
  "firstReleaseDate": 1471416753.488,
  "homepageLinkText": null,
  "homepageLinkUrl": null,
  "id": "amzn1.ask.skill.8a4844c1-bac6-4027-b0f2-7099235f5dc7",
  "imageAltText": "Motivation icon",
  "imageUrl": "https://github.com/dale3h/alexa-skills-list/raw/master/skills/B01KF22RE4/skill_icon",
  "inAppPurchasingSupported": false,
  "launchPhrase": "give motivation",
  "name": "Motivation",
  "numberOfReviews": 0,
  "pamsPartnerId": null,
  "permissions": null,
  "privacyPolicyUrl": null,
  "shortDescription": "Ask Alexa for motivation to spark your inner fire.",
  "skillTypes": null,
  "stage": "live",
  "termsOfUseUrl": null,
  "vendorId": "M34GWT20NMB3X8",
  "vendorName": "George Miranda"
}
