{
  "accountLinkingWhitelistedDomains": null,
  "asin": "B01MU1YKPU",
  "averageRating": 0,
  "canDisable": true,
  "capabilities": null,
  "category": null,
  "description": "Start a Seance! Talk to different spirits and learn about them by asking questions like \"Who are you?\", \"What's your name\" and \"How did you die?\" plus others. But you can only ask a couple of questions before they leave. Discover the stories of different people that may have more in common than even they think.\n\nSeance is a fun and enjoyable narrative game. Any resemblance to any persons living or dead is purely coincidental. We are not affiliated or endorsed by seancegame.com. Copyright 2016 Volta Software LLC.",
  "enablement": null,
  "exampleInteractions": [
    "Alexa start spirit seance",
    "Who are you?",
    "What are you?"
  ],
  "firstReleaseDate": 1483453413.419,
  "homepageLinkText": null,
  "homepageLinkUrl": null,
  "id": "amzn1.ask.skill.85539531-6923-4341-9b8d-f83ef31526a2",
  "imageAltText": "Spirit Seance icon",
  "imageUrl": "https://github.com/dale3h/alexa-skills-list/raw/master/skills/B01MU1YKPU/skill_icon",
  "inAppPurchasingSupported": false,
  "launchPhrase": "spirit seance",
  "name": "Spirit Seance",
  "numberOfReviews": 0,
  "pamsPartnerId": null,
  "permissions": null,
  "privacyPolicyUrl": null,
  "shortDescription": "Start a Seance and channel different spirits that you can talk to!",
  "skillTypes": null,
  "stage": "live",
  "termsOfUseUrl": null,
  "vendorId": "M9XFE97TDZBJ8",
  "vendorName": "Volta Software LLC"
}
