{
  "accountLinkingWhitelistedDomains": null,
  "asin": "B01IOYPK4Y",
  "averageRating": 5,
  "canDisable": true,
  "capabilities": null,
  "category": null,
  "description": "PDX Bus Tracker tells you arrivals for all buses for a given Stop ID. Invoke by calling Open PDX Bus Tracker, provide the Stop ID and it will respond with all Buses, Scheduled times and Next arrival times. Disclaimer; the app may not be suitable for all ages.",
  "enablement": null,
  "exampleInteractions": [
    "Alexa, Launch P. D. X. Bus Tracker.",
    "Alexa, Ask P. D. X. Bus Tracker for two two six six.",
    "Alexa, Ask P. D. X. Bus Tracker for help"
  ],
  "firstReleaseDate": 1470032788.15,
  "homepageLinkText": null,
  "homepageLinkUrl": null,
  "id": "amzn1.ask.skill.ec8d058d-0c81-4645-88be-f5a5b51c9b31",
  "imageAltText": "PDX Bus Tracker icon",
  "imageUrl": "https://github.com/dale3h/alexa-skills-list/raw/master/skills/B01IOYPK4Y/skill_icon",
  "inAppPurchasingSupported": false,
  "launchPhrase": "p. d. x. bus tracker",
  "name": "PDX Bus Tracker",
  "numberOfReviews": 1,
  "pamsPartnerId": null,
  "permissions": null,
  "privacyPolicyUrl": null,
  "shortDescription": "PDX Bus Tracker. Next Bus Arrivals for various Stop IDs in PDX",
  "skillTypes": null,
  "stage": "live",
  "termsOfUseUrl": null,
  "vendorId": "MUBKV1Q3QV3ML",
  "vendorName": "Afrilogic"
}
