{
  "accountLinkingWhitelistedDomains": null,
  "asin": "B01N5J1QDX",
  "averageRating": 0,
  "canDisable": true,
  "capabilities": null,
  "category": null,
  "description": null,
  "enablement": null,
  "exampleInteractions": null,
  "firstReleaseDate": 1483004976.758,
  "homepageLinkText": null,
  "homepageLinkUrl": null,
  "id": "amzn1.ask.skill.1f9212be-5b25-4528-bd2c-905488b6fb0d",
  "imageAltText": null,
  "imageUrl": "https://github.com/dale3h/alexa-skills-list/raw/master/skills/B01N5J1QDX/skill_icon",
  "inAppPurchasingSupported": false,
  "launchPhrase": null,
  "name": "Pub Quiz Questions HQ",
  "numberOfReviews": 0,
  "pamsPartnerId": null,
  "permissions": null,
  "privacyPolicyUrl": null,
  "shortDescription": null,
  "skillTypes": null,
  "stage": "live",
  "termsOfUseUrl": null,
  "vendorId": "M1W6PB0LHTBB9U",
  "vendorName": "Pub Quiz Questions HQ"
}
